<?xml version="1.0" encoding="utf-8" ?>
<dwsync>
<file name="danielquinn_ishmael.jpg" server="inside-out-html.kingbob4ever.com" local="132153823805280417" remote="131863788000000000" Dst="2" />
<file name="henry_david_thoreau.jpg" server="inside-out-html.kingbob4ever.com" local="132153823803278880" remote="131863788000000000" Dst="2" />
<file name="rye_catcher.jpg" server="inside-out-html.kingbob4ever.com" local="132153823803828981" remote="131863788000000000" Dst="2" />
<file name="the_case_for_christ.jpg" server="inside-out-html.kingbob4ever.com" local="132153823806062294" remote="131863788000000000" Dst="2" />
<file name="thecelestineprophecy.jpg" server="inside-out-html.kingbob4ever.com" local="132153823803759025" remote="131863788000000000" Dst="2" />
<file name="walden-thoreau.jpg" server="inside-out-html.kingbob4ever.com" local="132153823800816822" remote="131863788000000000" Dst="2" />
<file name="danielquinn_ishmael.jpg" server="2xx-1.kingbob4ever.com" local="132153972600000000" remote="132153972600000000" Dst="2" />
<file name="henry_david_thoreau.jpg" server="2xx-1.kingbob4ever.com" local="132153972600000000" remote="132153972600000000" Dst="2" />
<file name="rye_catcher.jpg" server="2xx-1.kingbob4ever.com" local="132153972600000000" remote="132153972600000000" Dst="2" />
<file name="the_case_for_christ.jpg" server="2xx-1.kingbob4ever.com" local="132153972600000000" remote="132153972600000000" Dst="2" />
<file name="thecelestineprophecy.jpg" server="2xx-1.kingbob4ever.com" local="132153972600000000" remote="132153972600000000" Dst="2" />
<file name="walden-thoreau.jpg" server="2xx-1.kingbob4ever.com" local="132153972600000000" remote="132153972600000000" Dst="2" />
</dwsync>